pyvns/LICENSE
pyvns/README.md
pyvns/__init__.cpython-311-x86_64-linux-gnu.so
pyvns/__init__.pyi
pyvns/py.typed
pyvns/vns_python_wrapper.cpython-311-x86_64-linux-gnu.so
pyvns/vns_python_wrapper.pyi
pyvns/__pyinstaller/__init__.py
pyvns/__pyinstaller/hook-pyvns.py
pyvns-2.3.dist-info/LICENSE
pyvns-2.3.dist-info/METADATA
pyvns-2.3.dist-info/WHEEL
pyvns-2.3.dist-info/entry_points.txt
pyvns-2.3.dist-info/top_level.txt
pyvns-2.3.dist-info/RECORD
