Metadata-Version: 2.1
Name: pyvns
Version: 2.3
Summary: VNS (Visual Novel Script), a universal scripting language for creating scripts for visual novel games.
Author-email: Linpg Foundation <yudong9912@gmail.com>
Project-URL: Homepage, https://github.com/LinpgFoundation/vns
Project-URL: Bug Tracker, https://github.com/LinpgFoundation/vns/issues
Classifier: Programming Language :: Python :: 3.10
Classifier: Programming Language :: Python :: 3.11
Classifier: Programming Language :: Python :: 3.12
Classifier: Programming Language :: Python :: Implementation :: CPython
Classifier: Operating System :: OS Independent
Requires-Python: >=3.10
License-File: LICENSE
Requires-Dist: mypy
